{
  "_id": 133,
  "name": "Instances",
  "modversion": "1.0.11",
  "gameversion": "2023r171p2",
  "loaderversion": "v0.6.1",
  "modtype": "Mod",
  "author": "kafeijao",
  "description": "__**Features**__:\n- Rejoin the last instance when restarting the game.\n- When rejoining teleport to the previous location.\n- When starting the game, join on an online Instance of the Home world.\n- Keep the joined Instances History and allow to rejoin them.\n- Restart the game via button.\n\nYou can toggle the joining last instance, or/and starting in an online instance, rejoining last Instance takes priority. Also you can configure the online instance region and privacy type.\n\nCheck [README.md](https://github.com/kafeijao/Kafe_CVR_Mods/tree/master/Instances) for more in-depth info.\n\n",
  "searchtags": [
    "rejoin",
    "history",
    "instance",
    "BTKUILib"
  ],
  "requirements": ["[BTKUILib](https://api.cvrmg.com/v1/mods/download/113)"],
  "downloadlink": "https://github.com/kafeijao/Kafe_CVR_Mods/releases/download/r56/Instances.dll",
  "sourcelink": "https://github.com/kafeijao/Kafe_CVR_Mods/tree/master/Instances",
  "changelog": "- Re-adding ChatBox integration.\n- Fixed borked instance names.",
  "embedcolor": "16C60C"
}
